README.md
setup.py
aiocached/__init__.py
aiocached/cache.py
aiocached/decorator.py
aiocached.egg-info/PKG-INFO
aiocached.egg-info/SOURCES.txt
aiocached.egg-info/dependency_links.txt
aiocached.egg-info/top_level.txt